README.md
setup.py
bin/dropbox-filemanager
dropbox_filemanager/__init__.py
dropbox_filemanager/client.py
dropbox_filemanager/main.py
dropbox_filemanager/version.py
dropbox_filemanager.egg-info/PKG-INFO
dropbox_filemanager.egg-info/SOURCES.txt
dropbox_filemanager.egg-info/dependency_links.txt
dropbox_filemanager.egg-info/requires.txt
dropbox_filemanager.egg-info/top_level.txt
icons/icon.png
icons/logo.png