Metadata-Version: 1.2
Name: dropbox-filemanager
Version: 1.0.2
Summary: An application to manage files in dropbox account
Home-page: https://gitlab.com/dslackw/dropbox-filemanager
Author: dslackw
Author-email: d.zlatanidis@gamil.com
License: UNKNOWN
Keywords: file,manager,dropbox
Platform: UNKNOWN
Classifier: Development Status :: 3 - Alpha
Classifier: Environment :: X11 Applications
Classifier: License :: OSI Approved :: MIT License
Classifier: Operating System :: POSIX
Classifier: Operating System :: POSIX :: Linux
Classifier: Programming Language :: Python
Classifier: Programming Language :: Python :: 3
Classifier: Programming Language :: Python :: 3.7
Requires-Python: >=3.7
